m2chart/__init__.py
m2chart/k8s.py
m2chart/main.py
m2chart/manifest2charts.py
m2chart/utils.py
m2chart/templates/app_templates/Chart.yaml
m2chart/templates/app_templates/requirements.yaml
m2chart/templates/app_templates/values.yaml
m2chart/templates/app_templates/templates/_helpers.tpl
m2chart/templates/app_templates/templates/configmap.yaml
m2chart/templates/app_templates/templates/pvc.yaml
m2chart/templates/app_templates/templates/secret.yaml
m2chart/templates/svc_templates/Chart.yaml
m2chart/templates/svc_templates/values.yaml
m2chart/templates/svc_templates/templates/_helpers.tpl
m2chart/templates/svc_templates/templates/daemonset.yaml
m2chart/templates/svc_templates/templates/deployment.yaml
m2chart/templates/svc_templates/templates/pvc.yaml
m2chart/templates/svc_templates/templates/service.yaml
m2chart/templates/svc_templates/templates/statefulset.yaml
m2chart-1.0.8.dist-info/METADATA
m2chart-1.0.8.dist-info/WHEEL
m2chart-1.0.8.dist-info/entry_points.txt
m2chart-1.0.8.dist-info/top_level.txt
m2chart-1.0.8.dist-info/zip-safe
m2chart-1.0.8.dist-info/RECORD
