Metadata-Version: 2.1
Name: m2chart
Version: 1.0.8
Summary: load online k8s workload manifest to a helm chart
Home-page: UNKNOWN
Author: yu.deng
Author-email: dengyu326@gmail.com
License: UNKNOWN
Platform: UNKNOWN
Classifier: Programming Language :: Python :: 3
Classifier: License :: OSI Approved :: MIT License
Classifier: Operating System :: OS Independent
Requires-Dist: pyyaml
Requires-Dist: kubernetes
